{
  "language": "vi",
  "duration": 1279.6981,
  "utterances": [
    {
      "start": 50.425,
      "end": 72.125,
      "text": "Hello xin chào tất cả mọi người mình là Mộc Miên và đây là kiến trúc sư Phạm Tuấn Anh Ngày hôm nay thì nhà chất đã quay trở lại với một công trình mà Miên tin rằng chỉ cần ngồi xem qua video thôi thì mọi người có thể cảm thấy sự thư thái thoải mái và dễ chịu khi ở đây và thực sự là có quá nhiều điều để nói về công trình này chúng ta sẽ bắt đầu ngay một phần giới thiệu ngắn gọn của anh Tuấn Anh Chào các bạn."
    },
    {
      "start": 72.445,
      "end": 74.605,
      "text": "Mình rất vui vì được đón"
    },
    {
      "start": 75.005005,
      "end": 80.045006,
      "text": "ban biên tập nhà chất đến tham quan trao đổi của mình về ngôi nhà này. Đây là"
    },
    {
      "start": 80.765,
      "end": 85.645004,
      "text": "ngôi nhà mà mình đã quyết định biến thành một ngôi nhà ở chính thức của mình chuyển từ"
    },
    {
      "start": 86.55,
      "end": 91.75,
      "text": "nội đô Hà Nội ra một vùng không chỉ ngoại ô mà còn là vùng"
    },
    {
      "start": 91.75,
      "end": 97.19,
      "text": "núi giáp ranh Hà Nội hòa bình Một không gian hoàn toàn khác nhìn sinh ra, lớn lên"
    },
    {
      "start": 97.83,
      "end": 107.435,
      "text": "và làm việc đều ở Hà Nội hơn bốn mươi năm nay và đến giờ thì mình quyết định là chuyển toàn bộ gia đình của mình vợ chồng con cái người đây ở Hà thì"
    },
    {
      "start": 107.595,
      "end": 117.77,
      "text": "mình thấy hoàn toàn happy và thấy rất là hài lòng với quyết định của mình ở đây thì rõ ràng ai cũng sẽ thấy là một nơi mà được thiên nhiên"
    },
    {
      "start": 118.25,
      "end": 119.21,
      "text": "ưu đãi"
    },
    {
      "start": 119.37,
      "end": 126.01,
      "text": "mang tặng rất là nhiều những món quà hậu hĩnh một vùng khí hậu của lừng nguyên sinh bao phủ xung quanh."
    },
    {
      "start": 126.57,
      "end": 127.450005,
      "text": "Rồi thì"
    },
    {
      "start": 128.17,
      "end": 130.49,
      "text": "những trường nhìn xa với những cánh đồng"
    },
    {
      "start": 130.96501,
      "end": 137.28502,
      "text": "trải dài dưới thung lũng. Thì ngoài những ưu đãi về mà thiên nhiên ra thì những cuộc sống ở"
    },
    {
      "start": 137.925,
      "end": 138.48502,
      "text": "vùng"
    },
    {
      "start": 139.285,
      "end": 141.76501,
      "text": "núi bọn mình còn có thêm một"
    },
    {
      "start": 142.16501,
      "end": 144.80501,
      "text": "điều tuyệt vời nữa đấy là những người mà muốn"
    },
    {
      "start": 145.04501,
      "end": 159.72,
      "text": "rất là yêu thiên nhiên, yêu sự bình yên đã cùng nhau tìm đến đây và tạo ra một cộng đồng gắn bó ở tại nơi này giữa một cái cuộc sống cũng rất là hiện đại và đang rất là vội vã ở trong lòng đơn vị Hà Nội của chúng ta ngày đây."
    },
    {
      "start": 160.41501,
      "end": 188.37502,
      "text": "Anh Tuấn Anh ơi, em có cảm giác là ngồi đây nghe anh chia sẻ thôi em cũng có thể cảm nhận được là một cái nhịp sống rất là ung dung thong dong không vội vã nhưng mà em nghĩ là khán giả cũng đang rất tò mò không biết là khi mà anh tới cái vùng đất này lần đầu tiên khi mà anh nhìn thấy một cái quả đồi nguyên sơ thì điều gì đã thúc đẩy anh quyết định là mình sẽ làm căn nhà đây Mình cũng đi một vài nơi và mình đã dừng chân tại nơi đây một nơi mà cũng có những cái phong cách khá gần với cả"
    },
    {
      "start": 188.615,
      "end": 190.375,
      "text": "Mỹ thành Hà Nội. Và"
    },
    {
      "start": 190.375,
      "end": 194.13501,
      "text": "có nhiều cái sự đồng điệu để khiến cho mình cảm thấy là ở đây là một cái"
    },
    {
      "start": 194.375,
      "end": 199.895,
      "text": "vùng đất rất là tuyệt vời để an cư. Vì mình là kiến trúc sư, đấy cho nên là"
    },
    {
      "start": 201.495,
      "end": 202.535,
      "text": "thường là"
    },
    {
      "start": 203.11,
      "end": 214.07,
      "text": "với bất cứ một cái mảnh đất nào thì mình cũng đều dễ dàng hình dung ra ngay là nên làm thế nào, nên tiếp cận như thế nào và sản phẩm cuối cùng nó sẽ là gì. Mình"
    },
    {
      "start": 214.07,
      "end": 224.76501,
      "text": "sẽ dựa vào những cái nguyên tắc cơ bản của ông cha. Mình đã từng vào Chúa từ rất nhiều đời nay là một ngôi nhà trên đồi thì lưng sẽ tựa vào đỉnh núi,"
    },
    {
      "start": 224.76501,
      "end": 225.16501,
      "text": "còn"
    },
    {
      "start": 226.205,
      "end": 259.44,
      "text": "mặt thì sẽ hướng về phía thung lũng giữ lại những cái cảnh quan hiện trạng tối đa để mà nương nhờ hoặc là tận hưởng những cái ưu đãi sẵn có của của địa hình địa vật. Và dường như là nó dựa được theo đúng cái thế đất nguyên bản ban đầu. Như anh chia sẻ thì em đang hiểu rằng ngôi nhà này được dựng lên dựa theo nương theo cái thế tự nhiên của đất cũng như là tận dụng tối đa những cái ưu đãi của thiên nhiên nơi đây và em đang ngồi ở vị trí này cái tầm giờ này em thấy đây là cái núm nắng đang rất là đẹp và một lát nữa thôi chắc là cái khoảng bên này sẽ đón được hoàng hôn đúng không anh đúng rồi Ở đây thì"
    },
    {
      "start": 259.91998,
      "end": 261.52,
      "text": "phía tây là cái phía"
    },
    {
      "start": 261.84,
      "end": 268.56,
      "text": "trường nhìn chính của khu đất. Nhưng phía nam là cái phía mà đón được nhiều những cái sinh khí,"
    },
    {
      "start": 269.12,
      "end": 272.88,
      "text": "gió lành và hiếp. Cho nên là khu nhà của mình được mở"
    },
    {
      "start": 273.52,
      "end": 276.615,
      "text": "nhiều hơn hai cái hướng đó. Anh ấy mình"
    },
    {
      "start": 276.695,
      "end": 282.935,
      "text": "đang ngồi với một móng cây cổ thụ rất là lớn, vừa có được cái móng mát rất là dễ chịu của"
    },
    {
      "start": 283.735,
      "end": 346.53,
      "text": "cây nhưng mà cũng vừa có được cái phần dính rất là tốt. Bản thân em thì cảm thấy rằng ngoài ở một công trình bình thường trên một mảnh đất bằng phẳng thì sẽ dễ thi công hơn rất là nhiều nhưng mà với một công trình mà ở trên một quả đồi như thế này đường đi lối lại đều là do mình phải tự tạo ra để mình có thể thuận lợi trong quá trình thi công thì đúng là những người mà có tư tưởng rời phố về quê mà lại còn ở trong cả đồi này nữa và thực sự em đoán rất là gia đình anh cũng phải rất là quyết tâm và có một cái sự yêu mến đặc biệt với vùng đất này với thiên nhiên nơi đây thì mới có thể quyết tâm để làm được một công trình mà vừa gần gũi với thiên nhiên mà vừa mang rất nhiều ý nghĩa như vậy chính vì thế mà ngày hôm nay thì em một quý vị khán giả của nhà chất cũng rất là mong muốn được đi trải nghiệm một vòng để cảm nhận hết những điều những câu chuyện mà anh Tuấn Anh muốn chia sẻ có được không ạ? Rất hân hạnh mời các bạn vào thông quan ngôi nhà của mình Dạ vâng ạ Và quý khán giả hãy cùng với Mục Viên đi trải nghiệm nha Liêm tin rằng là với công trình này thì quý vị chỉ cần xem qua màn hình thôi là cũng có thể cảm nhận được thiên nhiên đẹp như thế nào và cảm giác khoan khoái dễ chịu ra sao"
    },
    {
      "start": 397.96,
      "end": 429.77002,
      "text": "Để mọi người có thể tưởng tượng rõ nhất thì Nghiên đã đi xuống vị trí một lối đi của công trình và ở đây thì chúng ta có thể nhìn rất là rõ một cái cây đa mà anh Tuấn Anh vừa mô tả Đây là cây đã đã có từ rất lâu đời rồi và nhìn nó to như vậy thôi nhưng mà thật ra thì chỉ có cái thân này là cái thân cây Còn lại thì tất cả những cái nhánh được trễ ra đều là dễ cây theo thời gian đã phát triển hơn cũng như là mọc thêm những cái cành lá xung quanh nên là bây giờ một cây đa đã rất là to và trở thành biểu tượng của người dân này Ở đây thì là một trong những lối đi lên của công trình mà mọi người hãy theo Miên nhé cũng có rất là nhiều điều đặc biệt đấy"
    },
    {
      "start": 442.355,
      "end": 466.74,
      "text": "Bắt đầu từ lối đi lên này là mọi người có thể thấy rất là nhiều những đá tự nhiên ở đây và anh Tuấn Anh thì có chia sẻ rằng là tất cả những bậc thang đá này đều được thu thập từ đá bản địa và lát bằng tay nha mọi người nha nên là khi đi đến đây thì mình cảm thấy là một cái lối đi rất là dễ dàng nhưng mà cũng không kém phần gần gũi về thiên nhiên cảm giác như là đi trên một cái lối đi tự nhiên chứ không phải là do con người đắp đá vậy"
    },
    {
      "start": 481.00998,
      "end": 528.35504,
      "text": "Qua lối đi lên thì đón chúng ta sẽ là một chiếc xích đu ở ngay dưới gốc cây đa như thế này Tại vị trí này thì Miên có thể nghe rất là rõ tiếng nước chảy và tiếng thiên nhiên xung quanh Ngồi ở đây có một cái mùi cỏ cây rất là dễ chịu và ai có một bạn chó rất là xinh Ở đây thì anh chủ có chia sẻ là nuôi rất là nhiều cún ở đây bởi vì là theo địa hình ở đây thì sẽ phải nuôi những bạn cún này để có thể là bắt rắn và bắt chuột cho người dân ở nơi này nên là gần như những bạn cũ xung quanh đây thì rất là thân thiện với những người lên đây chơi Viên gặp rất là nhiều bạn rồi và khi mà ở đây thì Viên cảm thấy là anh Tuấn Anh cũng đầu tư rất là nhiều những khu tiểu cảnh nho nhỏ ví dụ như chiếc xích đu này để cho các thành viên trong gia đình có thể thoải mái làm những công việc riêng như là đọc sách hay là có những giờ phút vui chơi kết nối cùng với nhau"
    },
    {
      "start": 533.23,
      "end": 597.9,
      "text": "Đứng ở vị trí này mọi người biết không Liêm có thể đếm được rất nhiều những vị trí ghế ngồi này hay là đá tảng này hay là lều này để cho thay đổi không gian chúng ta ngồi ở đâu chúng ta có thể ngắm được view làm được việc ở đây là thấy có xích đu này trên này có một cái ghế này ở đây có hiên này ở kia có một cái bàn xong là lại bàn đá xa xa kia thì có lều nữa nên là không biết liệu có trải nghiệm được hết tất cả các không gian ở đây không Nếu mọi người vừa rồi nghe thấy tiếng nước chảy giống như Miên thì đây chính là một cái thác nước được anh Tuấn Anh làm rất là tâm huyết bởi vì anh có chia sẻ rằng là khi mà chúng ta bước ra khỏi nhà đi làm ở mỗi buổi sáng cũng như là trở về nhà sau mỗi ngày thì cái tiếng nước này nó sẽ như là một lời chào đón rất là dịu dàng đối với những căng thẳng mệt mỏi ở ngoài kia để chúng ta có thể trở về căn nhà bình yên của mình và đúng là với một thác nước được làm một cách đầu tư vào công phu dẫn tiểu cảnh và cây cối xung quanh thì khiến cho chúng ta cảm thấy rất là thoải mái thư thái một điều đặc biệt nữa là khu tiểu cảnh lại đối diện với hướng chính của căn nhà nên là ngồi ở trong ghế sofa nhìn ra thì sẽ giống như một bức tranh vậy ạ"
    },
    {
      "start": 605.02,
      "end": 626.96,
      "text": "Mọi người biết sao mặc dù tự mình đi trải nghiệm thôi không có anh Tuấn Anh đi cùng nhưng mà Miên cảm thấy rất là gần gũi thân thuộc bởi vì là mọi người có thể thấy ở đây là một bức tường đá thì đây cũng là cái đá bản địa thôi Anh Tuấn Anh toàn bộ sử dụng những vật liệu rất là thân thiện, gần gũi mộc mạc và toàn là vật liệu bản địa ví dụ ở đây là gỗ này, trên này là những lá"
    },
    {
      "start": 627.36005,
      "end": 634.72003,
      "text": "để tạo thành lán mái lợp như vậy thì sẽ mang đến một cảm giác rất là hòa quyện về thiên nhiên cũng như là mình có thể cảm nhận được"
    },
    {
      "start": 635.28,
      "end": 666.755,
      "text": "hồn của người dân bản địa ở đây hồn của ngọn núi ngọn đồi này và Miên cũng có một cảm giác tương tự như vậy mặc dù đây là lần đầu tiên đến đây và cũng rất háo hức muốn chia sẻ với mọi người về cái hàng hiên này đây là phía hông của căn nhà và phía hông này thì lại đối diện với hướng tây ở trước mặt này là hướng tây và chúng ta sẽ nhìn ra thung lũng rất là đẹp ở đằng xa kia thì có những ngọn núi chập trùng thì đúng là ngồi đây thì phải gọi là view quá là đỉnh để có thể làm việc hay làm bất kỳ một điều gì khác thì cũng đều rất là thích và"
    },
    {
      "start": 667.075,
      "end": 704.585,
      "text": "tâm này Miên đang ở đây là lúc mà hoàng hôn nên là vừa nãy sẽ có rất là nhiều nắng chiếu vào đây mình cảm giác không biết sao nữa nhưng mà chỉ muốn ở đây mãi thôi và nếu như mà có cơ hội là mình sẽ muốn nám lại đây để đọc sách để làm việc và cùng với đó thì anh Tuấn Anh cũng chia sẻ với Yên một vài giải pháp để có thể khắc phục cho cái hướng tây đó là có một cái thảm cỏ tự nhiên ở đằng trước này và ở đây thì cái hiên rất là rộng trải dài từ phía này cho đến tít đằng phía kia mới hết thì chúng ta sẽ tận dụng được cái không gian hiên này để làm hành lang đẩy ra ngoài kết nối giữa các phòng các thành viên trong gia đình và anh có chia sẻ một câu chuyện rất là đáng yêu đấy là có những"
    },
    {
      "start": 704.90497,
      "end": 720.16003,
      "text": "ngày hè mà trời mát mát là cả gia đình anh có thể ra đây nằm ngủ trưa luôn một điều mà rất là thú vị tất nhiên là thẩm mỹ cũng quan trọng nhưng mà cái việc mà chúng ta tạo ra những cái ý nghĩa hay là những cái sợi dây kết nối giữa các thành viên trong gia đình cũng là một điều quan trọng hơn nữa"
    },
    {
      "start": 738.395,
      "end": 788.755,
      "text": "Không biết là xem qua video thì mọi người có cảm nhận rõ hay không Miên đang đứng ở một vị trí khác với một tầm view khác rồi không phải là view vừa nãy nữa đâu Bởi vì là đi xung quanh công trình này thì mình có thể hướng mắt ra rất nhiều những cảnh đẹp khác nhau Và một trong những chia sẻ mà Miên ấn tượng nhất về anh Tuấn Anh đấy là anh rất quan tâm đến chất lượng cuộc sống gia đình cũng như là việc đầu tư thời gian và nâng cao chất lượng cuộc sống chất lượng trải nghiệm cho các bạn nhỏ trong nhà chính vì vậy mà một khu camping như thế này Miên nghĩ là rất là ấn tượng để cho các bạn có thêm trải nghiệm của người bố mẹ thay đổi không gian cũng là một cách để giúp các bạn có thêm nhiều nguồn cảm hứng trong học tập cũng như trong cuộc sống hàng ngày ngoài ra thì đây cũng sẽ là một tụ điểm lý tưởng dành cho những người bạn của vợ chồng anh Tuấn Anh khi mà cuối tuần có thể lên đây vừa nghỉ dưỡng vừa trải nghiệm thiên nhiên và mang theo những bạn nhỏ để tạo ra những trò chơi cũng là những trải nghiệm hay hơn nữa"
    },
    {
      "start": 804.77997,
      "end": 829.82,
      "text": "Đây sẽ là không gian chính của công trình và tại đây thì viên có thể nhìn thấy là phòng khách này phòng bếp và phòng ngủ được gộp chung lại một không gian khiến cho mọi thứ trở nên rất là rộng và ăn gian diện tích ở mọi người Ở đây thì phòng khách sẽ nhìn thẳng ra cái hướng cửa chính này là hướng nam Anh Tuấn Anh cũng đã chia sẻ trước với chúng ta ở đó và ngồi ở vị trí này thì chúng ta có thể nhìn ra cái khu tiểu cảnh vừa nãy trông rất giống như là một bức tranh"
    },
    {
      "start": 832.14,
      "end": 867.17,
      "text": "Miên nghĩ là phải trực tiếp trải nghiệm ở đây thì mọi người mới cảm thấy là mọi thứ nó thân thuộc ra sao bởi vì Miên thấy là mọi chi tiết trong gia đình anh Tuấn Anh đều không cầu kỳ mọi thứ đều rất gần gũi và cảm giác như là thiên nhiên rồi những sự kết nối mới chính là sợi dây gắn kết xuyên suốt giữa cả công trình và ở đây thì bộ sofa này Miên cảm thấy rất là độc đáo khi mà anh Tuấn Anh cũng có những sự nhắc lại đối với những khối gỗ lớn như thế này để tận dụng lại một sự liên kết cho căn nhà Bên cạnh đó cũng tạo ra một sự thú vị đối với những người đến chơi, khách đến chơi, ngồi phòng khách như thế này"
    },
    {
      "start": 868.13,
      "end": 916.58997,
      "text": "Và hệ mái của công trình này thì cũng được thiết kế khá là ấn tượng mặc dù là vẫn tối giản thôi nhưng mà trông cũng rất là ấn tượng và anh Tuấn Anh có chia sẻ rằng cả công trình này thì được làm bằng khung thép chính vì vậy là cái thời gian để thi công thì nó sẽ rất là nhanh và có một lợi thế nữa đó là chẳng hạn như sau này mình có không muốn ở đây nữa mình muốn chuyển đi nơi khác thì mình hoàn toàn có thể di chuyển cái khung thép này đến một nơi khác và dựng lên một công trình cũng tương tự như thế này chẳng hạn Nhưng mà Miên nghĩ rằng là có một công trình ở đây người khác muốn sở hữu đôi khi không được chứ ai lỡ chuyển đi đúng không mọi người và để nói với một điểm nhấn nữa trong không gian phòng khách này thì Miên nghĩ đó chính là cái hệ tủ bếp mà không phải tủ bếp mà đây có thể gọi là khu vực quầy bar đồng thời cũng là khu vực bếp này bởi vì ở đây sẽ có một tấm gỗ rất là lớn mà ở dưới nó làm thép"
    },
    {
      "start": 916.67,
      "end": 931.085,
      "text": "vật liệu rất là vững chắc mọi người ạ với những họa tiết mà trông cũng rất là lạ mắt nha Ở đây thì gia chủ có kết hợp để một chiếc tivi để vừa làm không gian của phòng khách cả gia đình có thể xem tivi mà vừa cũng gắn với khu"
    },
    {
      "start": 931.085,
      "end": 981.32,
      "text": "vực phòng bếp này tận dụng tối ưu không gian không bị trưng ra quá nhiều kệ tủ nên Liêm nghĩ rằng đây cũng sẽ là một điểm nhấn rất là thú vị cho căn nhà và mọi vật liệu thì cảm giác đều rất là thân thuộc gần gũi chứ không hề bị phô trương hay là quá cầu kỳ đâu Nhi nghĩ là công trình này có một cái ưu thế rất là lớn đó là bao quanh toàn là thiên nhiên núi đồi và cây cối Ở đây Nhi có thể nhìn rõ là hướng này cũng thấy thiên nhiên này rất là xanh ở đằng này cũng thấy thiên nhiên xanh và đặc biệt là ở khu bếp này cũng là thiên nhiên xanh Khi mà được đi trải nghiệm và tham quan các công trình thì Miên rất là ấn tượng với những công trình mà chăm chút cho căn bếp bởi vì theo Miên thì căn bếp sẽ là nơi giữ lửa của gia đình nên là sẽ cần một không gian mà nó hiện đại hơn nó thay đổi một chút về những cái gì truyền thống như kiểu là bó hẹp và rất là bí thì không gian này đã mở ra và có rất là nhiều điểm sáng tạo"
    },
    {
      "start": 982.565,
      "end": 986.725,
      "text": "ví dụ như ở đây thì đây là hướng đông của căn nhà"
    },
    {
      "start": 987.125,
      "end": 990.485,
      "text": "Tuấn Anh đã mở ra một cái ô cửa rất là lớn"
    },
    {
      "start": 993.045,
      "end": 994.725,
      "text": "còn thật sự rất là lớn ấy"
    },
    {
      "start": 995.605,
      "end": 1019.735,
      "text": "với hướng đông này đây chính là đỉnh của ngọn núi rồi nên xung quanh cũng sẽ có những hàng cây và thiên nhiên nói chung là có một mảng xanh để khi ai đó đứng đây nấu bếp thì sẽ có một tâm trạng rất là thoải mái vui vẻ và cảm giác được hòa hợp với thiên nhiên Nguyên thì Nguyên luôn tin rằng là nếu như mà tâm trạng của người nấu và tốt thì cũng sẽ nấu ra những món ăn ngon bên cạnh đó thì anh Tuấn Anh cũng có chia sẻ thêm rằng"
    },
    {
      "start": 1020.055,
      "end": 1027.19,
      "text": "khi mà chúng ta thiết kế bếp như thế này thì gió thổi vào cũng sẽ khiến cho mọi thứ được khô ráo không bị ẩm thấp và gây"
    },
    {
      "start": 1027.35,
      "end": 1067.525,
      "text": "đến tình trạng bị mốc chẳng hạn Thế là nên rất là ấn tượng với thiết kế căn bếp như thế này Từ căn bếp này thì chúng ta sẽ di chuyển ra khu vực phòng ăn đây là có một cái bàn năng khá là lớn cũng làm bằng chất liệu gỗ thôi để mọi thứ trở nên thân thuộc hơn và có một điều mà Miên đã để ý ngay từ khi đến thân công trình này đó là ở bên trong nội thất thì cũng rất là tối giản và tất cả những thứ mà làm lên linh hồn ở bên trong thì đều là những cái kỷ vật cũng như là kỷ niệm của gia đình vợ chồng con cái rất là nhiều cút rồi sách tất cả mọi thứ này đều gắn với một câu chuyện một kỷ niệm nào đấy của vợ chồng anh Tuấn Anh và hai con của mình Đấy là cái mà Viên cảm thấy nó có thể giữ lửa và giữ hồn cho công trình này rất là nhiều"
    },
    {
      "start": 1068.165,
      "end": 1143,
      "text": "Mọi người có thể để ý rằng là nếu như bây giờ chúng ta có những vách ngăn cho những không gian phòng khách phòng bếp và phòng ngủ thì có vẻ như mọi thứ cũng sẽ khá là chật lận bởi vì đây cũng không phải là một diện tích lớn nhưng mà khi mà anh Tuấn Anh áp dụng vào một cái giải pháp là ăn gian không gian kết nối mọi thứ thông nhau như thế này thì cảm thấy là ở đâu cũng rộng ở đâu cũng có thể thoáng và ở đâu có thể nhìn ra thiên nhiên Nhưng mà sẽ có những bạn có thắc mắc giống viên đúng không? Đó là nếu như phòng ăn và phòng bếp rồi phòng khách lại còn tiện với nhau như thế này, thông với nhau như thế này nối liền với phòng ngủ thì sẽ rất là bất tiện cho vợ chồng gia chủ Thế nhưng anh Tuấn Anh đã có thiết kế một cái cửa xếp ở đây để trong những trường hợp ví dụ như là khi mà chúng ta cần không gian để nghỉ ngơi để ngủ nghỉ thì có thể kéo cửa xếp này xuống vẫn đảm bảo được sự riêng tư nhưng mà khi mà bình thường như thế này thì chúng ta sẽ kéo cửa lên để không gian nhà có một sự xuyên suốt và cảm giác rất là rộng rất là thoáng không biết là mọi người xem video có thể cảm nhận được không mọi người có thể comment ở dưới Ở trong công trình này thì Miên nghĩ rằng Miên sẽ khen hơi nhiều vì thực sự là mình là một người rất dễ rung động với những công trình kết nối với thiên nhiên cách tối đa và lại có linh hồn của căn nhà bởi những kỷ niệm kỷ vật của những người trong gia đình nên là mọi người thông cảm chút xíu"
    },
    {
      "start": 1190.4099,
      "end": 1220.36,
      "text": "Mọi người biết sao không? Khi mà chúng ta có những trải nghiệm đọc sách ở những không gian khác nhau thì sự tiếp thu của chúng ta sự tiếp nhận nội dung của chúng ta cũng rất là khác nhau có những ngày thì mình đọc sách nhưng thực sự là mình không tập trung nổi hay là có những ngày mà mình rất muốn đọc sách nhưng mà cái việc hấp thụ nội dung hay là cái việc mà mình đọc cái nội dung đó mình cảm thấy là không hiểu mình cảm thấy là nó cứ sao sao nó không vào trong đầu mình là những chuyện mà có thật nha nhưng mà ngày hôm nay thì khi được ngồi ở một không gian như thế này giữa thiên nhiên bao quanh"
    },
    {
      "start": 1221,
      "end": 1233.095,
      "text": "được nghe tiếng nước chảy này tiếng chim hót tiếng người dân bản miệng thì mình cảm thấy là mình như được hòa với không gian này luôn và ngồi đọc sách cảm thấy mọi thứ nó ngấm từng câu từng chữ ở trong đầu mình ý và"
    },
    {
      "start": 1233.415,
      "end": 1265.835,
      "text": "Minh nghĩ rằng đây là một trong những trải nghiệm đọc sách ấn tượng nhất của mình luôn phải nói ra là số ngày hôm nay thì khen hơn nhiều nhưng mà mong mọi người thông cảm vì mình cũng là một người mà rất là dễ rung động với những thiên nhiên xung quanh và đúng là trải nghiệm ngày hôm nay là một trong những trải nghiệm mà Miên cảm thấy như kiểu mình được gạt tất cả mọi thứ sang một bên và chỉ có cảm nhận cảm nhận có những cái mà mình không mô tả được bằng lời mà chỉ có cảm nhận và cảm xúc thôi mong là mọi người cũng có thể cảm nhận được một chút nào đó năng lượng của Miên và những cái cảm xúc của Miên khi trải nghiệm công trình này ở phần"
    },
    {
      "start": 1266.235,
      "end": 1277.2632,
      "text": "xem video ngày hôm nay và nếu như mọi người có thêm chia sẻ gì cảm nhận của mọi người về công trình ngày hôm nay ra sao thì mọi người có thể comment ở phía dưới để chúng ta kết nối với nhau nhiều hơn nhé. Cảm ơn mọi người rất nhiều!"
    }
  ]
}